vectice/__init__.py
vectice/__version__.py
vectice/connection.py
vectice/py.typed
vectice/api/__init__.py
vectice/api/_auth.py
vectice/api/_utils.py
vectice/api/attachment.py
vectice/api/client.py
vectice/api/columns_description.py
vectice/api/compatibility.py
vectice/api/gql_api.py
vectice/api/gql_attachment.py
vectice/api/gql_dataset.py
vectice/api/gql_feature_flag.py
vectice/api/gql_issue.py
vectice/api/gql_lineage.py
vectice/api/gql_metric.py
vectice/api/gql_model.py
vectice/api/gql_organization.py
vectice/api/gql_phase.py
vectice/api/gql_property.py
vectice/api/gql_report.py
vectice/api/gql_review.py
vectice/api/gql_user_workspace_api.py
vectice/api/http_error.py
vectice/api/http_error_handlers.py
vectice/api/iteration.py
vectice/api/json_object.py
vectice/api/project.py
vectice/api/project_template.py
vectice/api/rest_api.py
vectice/api/version.py
vectice/api/workspace.py
vectice/api/json/__init__.py
vectice/api/json/artifact_version.py
vectice/api/json/attachment.py
vectice/api/json/code.py
vectice/api/json/code_version.py
vectice/api/json/compatibility.py
vectice/api/json/dataset_register.py
vectice/api/json/dataset_representation.py
vectice/api/json/dataset_resource_representation.py
vectice/api/json/dataset_version.py
vectice/api/json/dataset_version_representation.py
vectice/api/json/entity_file.py
vectice/api/json/files_metadata.py
vectice/api/json/issue.py
vectice/api/json/iteration.py
vectice/api/json/json_to_class.py
vectice/api/json/json_type.py
vectice/api/json/last_assets.py
vectice/api/json/metric.py
vectice/api/json/model.py
vectice/api/json/model_register.py
vectice/api/json/model_representation.py
vectice/api/json/model_version.py
vectice/api/json/model_version_representation.py
vectice/api/json/organization_config.py
vectice/api/json/page.py
vectice/api/json/paged_response.py
vectice/api/json/phase.py
vectice/api/json/project.py
vectice/api/json/project_template.py
vectice/api/json/property.py
vectice/api/json/public_config.py
vectice-25.4.2.0.dist-info/licenses/LICENSE
vectice-25.4.2.0.dist-info/METADATA
vectice-25.4.2.0.dist-info/WHEEL
vectice-25.4.2.0.dist-info/top_level.txt
vectice-25.4.2.0.dist-info/RECORD
