Metadata-Version: 2.4
Name: vectice
Version: 25.4.2.0
Summary: Vectice Python library
Home-page: https://www.vectice.com
Author: Vectice Inc.
Author-email: sdk@vectice.com
License: Apache License 2.0
Keywords: Vectice,Client,API,Adapter
Platform: Linux
Platform: MacOS X
Platform: Windows
Classifier: Topic :: Internet
Classifier: Topic :: Scientific/Engineering :: Artificial Intelligence
Classifier: Topic :: Software Development :: Libraries :: Python Modules
Classifier: Development Status :: 5 - Production/Stable
Classifier: License :: OSI Approved :: Apache Software License
Classifier: Programming Language :: Python :: 3 :: Only
Classifier: Programming Language :: Python :: 3.9
Classifier: Programming Language :: Python :: 3.10
Classifier: Programming Language :: Python :: 3.11
Classifier: Programming Language :: Python :: 3.12
Classifier: Operating System :: OS Independent
Classifier: Intended Audience :: Developers
Classifier: Intended Audience :: Science/Research
Classifier: Natural Language :: English
Classifier: Typing :: Typed
Requires-Python: >=3.9.0
License-File: LICENSE
Requires-Dist: types-python-dateutil
Requires-Dist: python-dotenv>=0.11.0
Requires-Dist: requests<=2.32.4
Requires-Dist: rich
Requires-Dist: urllib3<=2.5.0
Requires-Dist: gql[requests]>=4.0.0
Requires-Dist: GitPython
Requires-Dist: matplotlib
Requires-Dist: packaging
Requires-Dist: Pillow
Requires-Dist: pandas
Requires-Dist: typing-extensions>=4.5.0
Requires-Dist: dataclasses-json==0.5.8
Requires-Dist: IPython
Requires-Dist: ipynbname
Provides-Extra: dev
Requires-Dist: black==24.2.0; extra == "dev"
Requires-Dist: gitpython; extra == "dev"
Requires-Dist: pyright==1.1.360; extra == "dev"
Requires-Dist: ruff; extra == "dev"
Requires-Dist: types-requests; extra == "dev"
Requires-Dist: types-urllib3; extra == "dev"
Requires-Dist: types-mock; extra == "dev"
Requires-Dist: mypy_boto3_s3==1.34.65; extra == "dev"
Requires-Dist: pandas-stubs; extra == "dev"
Provides-Extra: doc
Requires-Dist: black==24.2.0; extra == "doc"
Requires-Dist: markdown-callouts>=0.2; extra == "doc"
Requires-Dist: markdown-exec>=1.2; extra == "doc"
Requires-Dist: mkdocs; extra == "doc"
Requires-Dist: mkdocs-material>=7.3; extra == "doc"
Requires-Dist: mkdocs-redirects>=1.2; extra == "doc"
Requires-Dist: mkdocs-section-index>=0.3; extra == "doc"
Requires-Dist: mkdocstrings[python]>=0.18; extra == "doc"
Provides-Extra: test
Requires-Dist: docker==7.1.0; extra == "test"
Requires-Dist: docker-compose; extra == "test"
Requires-Dist: dslr[psycopg2-binary]; extra == "test"
Requires-Dist: mock>=1.0.1; extra == "test"
Requires-Dist: numpy; extra == "test"
Requires-Dist: pytest==8.2.0; extra == "test"
Requires-Dist: pytest-randomly; extra == "test"
Requires-Dist: coverage; extra == "test"
Requires-Dist: pytest-cov; extra == "test"
Requires-Dist: pydrive2; extra == "test"
Requires-Dist: scikit-learn<=1.6.1; extra == "test"
Requires-Dist: testcontainers; extra == "test"
Requires-Dist: db-dtypes>=1.1.1; extra == "test"
Requires-Dist: pyspark; extra == "test"
Requires-Dist: mlflow<=2.22.1; extra == "test"
Requires-Dist: Cython>=3.0; extra == "test"
Requires-Dist: pyyaml==5.3.1; extra == "test"
Requires-Dist: pyarrow>=15.0.0; python_version >= "3.12" and extra == "test"
Requires-Dist: IPython; extra == "test"
Requires-Dist: matplotlib; extra == "test"
Requires-Dist: papermill; extra == "test"
Requires-Dist: tenacity==8.3.0; extra == "test"
Requires-Dist: plotly; extra == "test"
Requires-Dist: ipynbname; extra == "test"
Requires-Dist: nbformat; extra == "test"
Requires-Dist: lightgbm; extra == "test"
Requires-Dist: catboost; extra == "test"
Requires-Dist: tensorflow>=2.15.1; extra == "test"
Requires-Dist: keras; extra == "test"
Requires-Dist: snowflake-snowpark-python; extra == "test"
Requires-Dist: seaborn; extra == "test"
Requires-Dist: statsmodels; extra == "test"
Requires-Dist: xgboost; extra == "test"
Requires-Dist: kaleido; extra == "test"
Requires-Dist: torch; extra == "test"
Requires-Dist: ipywidgets; extra == "test"
Requires-Dist: polars; extra == "test"
Requires-Dist: wandb; extra == "test"
Provides-Extra: gcs
Requires-Dist: google-cloud-storage>=1.17.0; extra == "gcs"
Requires-Dist: google-cloud-bigquery; extra == "gcs"
Requires-Dist: protobuf; extra == "gcs"
Provides-Extra: s3
Requires-Dist: boto3; extra == "s3"
Provides-Extra: validation
Requires-Dist: shap>=0.44.1; extra == "validation"
Requires-Dist: scipy<=1.12; extra == "validation"
Dynamic: author
Dynamic: author-email
Dynamic: classifier
Dynamic: description
Dynamic: description-content-type
Dynamic: home-page
Dynamic: keywords
Dynamic: license
Dynamic: license-file
Dynamic: platform
Dynamic: provides-extra
Dynamic: requires-dist
Dynamic: requires-python
Dynamic: summary
